{
  "file_name": "multianimal_02412.jpg",
  "dataset": "animal-90-multianimal",
  "objects": [
    {
      "class": "squirrel",
      "bbox": [
        0.3046875,
        0.4375,
        0.296875,
        0.3958333333333333
      ]
    },
    {
      "class": "seahorse",
      "bbox": [
        0.515625,
        0.4270833333333333,
        0.2328125,
        0.3104166666666667
      ]
    },
    {
      "class": "dragonfly",
      "bbox": [
        0.159375,
        0.6104166666666667,
        0.1734375,
        0.23125
      ]
    }
  ]
}