{
  "file_name": "multianimal_00160.jpg",
  "dataset": "animal-90-multianimal",
  "objects": [
    {
      "class": "chimpanzee",
      "bbox": [
        0.2390625,
        0.14583333333333334,
        0.203125,
        0.2708333333333333
      ]
    },
    {
      "class": "bison",
      "bbox": [
        0.10625,
        0.15208333333333332,
        0.2921875,
        0.38958333333333334
      ]
    },
    {
      "class": "hare",
      "bbox": [
        0.2625,
        0.46875,
        0.121875,
        0.1625
      ]
    },
    {
      "class": "porcupine",
      "bbox": [
        0.1203125,
        0.4375,
        0.2640625,
        0.35208333333333336
      ]
    }
  ]
}