{
  "file_name": "multianimal_00085.jpg",
  "dataset": "animal-90-multianimal",
  "objects": [
    {
      "class": "flamingo",
      "bbox": [
        0.6671875,
        0.20625,
        0.3,
        0.4
      ]
    },
    {
      "class": "raccoon",
      "bbox": [
        0.3515625,
        0.49166666666666664,
        0.25,
        0.3333333333333333
      ]
    },
    {
      "class": "hyena",
      "bbox": [
        0.421875,
        0.44583333333333336,
        0.2078125,
        0.27708333333333335
      ]
    },
    {
      "class": "lobster",
      "bbox": [
        0.109375,
        0.26666666666666666,
        0.303125,
        0.4041666666666667
      ]
    }
  ]
}