{
  "file_name": "multianimal_02220.jpg",
  "dataset": "animal-90-multianimal",
  "objects": [
    {
      "class": "caterpillar",
      "bbox": [
        0.1125,
        0.6166666666666667,
        0.128125,
        0.17083333333333334
      ]
    },
    {
      "class": "goat",
      "bbox": [
        0.0265625,
        0.4791666666666667,
        0.3234375,
        0.43125
      ]
    },
    {
      "class": "rhinoceros",
      "bbox": [
        0.2046875,
        0.4166666666666667,
        0.334375,
        0.44583333333333336
      ]
    }
  ]
}