{
  "file_name": "multianimal_01170.jpg",
  "dataset": "animal-90-multianimal",
  "objects": [
    {
      "class": "goose",
      "bbox": [
        0.04375,
        0.28125,
        0.1859375,
        0.24791666666666667
      ]
    },
    {
      "class": "hedgehog",
      "bbox": [
        0.1328125,
        0.5479166666666667,
        0.3015625,
        0.40208333333333335
      ]
    },
    {
      "class": "octopus",
      "bbox": [
        0.2734375,
        0.125,
        0.121875,
        0.1625
      ]
    },
    {
      "class": "seahorse",
      "bbox": [
        0.6375,
        0.14791666666666667,
        0.1265625,
        0.16875
      ]
    }
  ]
}