{
  "file_name": "multianimal_00151.jpg",
  "dataset": "animal-90-multianimal",
  "objects": [
    {
      "class": "penguin",
      "bbox": [
        0.7203125,
        0.6604166666666667,
        0.1625,
        0.21666666666666667
      ]
    },
    {
      "class": "oyster",
      "bbox": [
        0.3875,
        0.14375,
        0.3375,
        0.45
      ]
    },
    {
      "class": "zebra",
      "bbox": [
        0.403125,
        0.5270833333333333,
        0.340625,
        0.45416666666666666
      ]
    },
    {
      "class": "mosquito",
      "bbox": [
        0.671875,
        0.47291666666666665,
        0.2140625,
        0.28541666666666665
      ]
    }
  ]
}