{
  "file_name": "multianimal_00290.jpg",
  "dataset": "animal-90-multianimal",
  "objects": [
    {
      "class": "ox",
      "bbox": [
        0.278125,
        0.4625,
        0.296875,
        0.3958333333333333
      ]
    },
    {
      "class": "bear",
      "bbox": [
        0.3625,
        0.7958333333333333,
        0.146875,
        0.19583333333333333
      ]
    },
    {
      "class": "seahorse",
      "bbox": [
        0.50625,
        0.40625,
        0.3328125,
        0.44375
      ]
    },
    {
      "class": "hare",
      "bbox": [
        0.8625,
        0.6020833333333333,
        0.128125,
        0.17083333333333334
      ]
    }
  ]
}