{
  "file_name": "multianimal_01783.jpg",
  "dataset": "animal-90-multianimal",
  "objects": [
    {
      "class": "mosquito",
      "bbox": [
        0.4328125,
        0.5229166666666667,
        0.19375,
        0.25833333333333336
      ]
    },
    {
      "class": "swan",
      "bbox": [
        0.6546875,
        0.01875,
        0.25,
        0.3333333333333333
      ]
    },
    {
      "class": "eagle",
      "bbox": [
        0.2109375,
        0.46875,
        0.3109375,
        0.41458333333333336
      ]
    },
    {
      "class": "pig",
      "bbox": [
        0.546875,
        0.1875,
        0.178125,
        0.2375
      ]
    }
  ]
}